apptax/__init__.py
apptax/app.py
apptax/database.py
apptax/docker_config.py
apptax/admin/__init__.py
apptax/admin/admin.py
apptax/admin/admin_view.py
apptax/admin/filters.py
apptax/admin/forms.py
apptax/admin/mixins.py
apptax/admin/utils.py
apptax/admin/static/logo_inpn.png
apptax/admin/static/images/pictos/amphibien.gif
apptax/admin/static/images/pictos/araignee.gif
apptax/admin/static/images/pictos/champignon.gif
apptax/admin/static/images/pictos/ecrevisse.gif
apptax/admin/static/images/pictos/favicon.png
apptax/admin/static/images/pictos/insecte.gif
apptax/admin/static/images/pictos/mammifere.gif
apptax/admin/static/images/pictos/mollusque.gif
apptax/admin/static/images/pictos/mousse.gif
apptax/admin/static/images/pictos/nopicto.gif
apptax/admin/static/images/pictos/oiseau.gif
apptax/admin/static/images/pictos/picto_Angiospermes.png
apptax/admin/static/images/pictos/picto_Annelides.png
apptax/admin/static/images/pictos/picto_Bivalves.png
apptax/admin/static/images/pictos/picto_Fougeres.png
apptax/admin/static/images/pictos/picto_Gasteropodes.png
apptax/admin/static/images/pictos/picto_Gymnospermes.png
apptax/admin/static/images/pictos/picto_Mammiferes.png
apptax/admin/static/images/pictos/picto_Myriapodes.png
apptax/admin/static/images/pictos/plante.gif
apptax/admin/static/images/pictos/poisson.gif
apptax/admin/static/images/pictos/reptile.gif
apptax/admin/static/images/pictos/squelette.png
apptax/admin/static/js/login.js
apptax/admin/static/js/regne_group2_inpn.js
apptax/admin/static/js/taxref_autocomplete.js
apptax/admin/templates/admin/custom_row_actions.html
apptax/admin/templates/admin/details_taxref.html
apptax/admin/templates/admin/edit_attr.html
apptax/admin/templates/admin/edit_bib_list.html
apptax/admin/templates/admin/edit_taxref.html
apptax/admin/templates/admin/list_biblist.html
apptax/admin/templates/admin/list_taxref.html
apptax/admin/templates/admin/login.html
apptax/admin/templates/admin/populate_biblist.html
taxhub-2.2.3.dist-info/licenses/LICENSE
taxhub-2.2.3.dist-info/METADATA
taxhub-2.2.3.dist-info/WHEEL
taxhub-2.2.3.dist-info/entry_points.txt
taxhub-2.2.3.dist-info/top_level.txt
taxhub-2.2.3.dist-info/RECORD
