Metadata-Version: 2.4
Name: taxhub
Version: 2.2.3
Summary: Application web de gestion centralisée des taxons basée sur le référentiel TAXREF
Home-page: https://github.com/PnX-SI/TaxHub
Maintainer: Parcs nationaux des Écrins et des Cévennes
Maintainer-email: geonature@ecrins-parcnational.fr
License-File: LICENSE
Requires-Dist: Flask<4
Requires-Dist: Flask-Admin
Requires-Dist: Flask-Cors
Requires-Dist: Flask-SQLAlchemy<3.1
Requires-Dist: Flask-Migrate
Requires-Dist: Flask-Babel
Requires-Dist: marshmallow-sqlalchemy
Requires-Dist: gunicorn>=19.8.0
Requires-Dist: SQLAlchemy<2.0
Requires-Dist: psycopg2
Requires-Dist: python-dotenv
Requires-Dist: Pillow
Requires-Dist: urllib3
Requires-Dist: click>=8.1.3
Requires-Dist: toml
Requires-Dist: wtforms==3.1.2
Requires-Dist: backports.entry-points-selectable
Requires-Dist: utils-flask-sqlalchemy<1.0,>=0.4.2
Requires-Dist: pypnusershub<4,>=3.0.3
Requires-Dist: pypn-ref-geo<2.0,>=1.5.5
Provides-Extra: tests
Requires-Dist: pytest; extra == "tests"
Requires-Dist: pytest-flask; extra == "tests"
Requires-Dist: pytest-cov; extra == "tests"
Requires-Dist: schema; extra == "tests"
Dynamic: description
Dynamic: description-content-type
Dynamic: home-page
Dynamic: license-file
Dynamic: maintainer
Dynamic: maintainer-email
Dynamic: provides-extra
Dynamic: requires-dist
Dynamic: summary
